README.md
setup.py
rubik/__init__.py
rubik/logger.py
rubik/metrics.py
rubik/rubik.py
rubik/utils.py
rubik_pytorch.egg-info/PKG-INFO
rubik_pytorch.egg-info/SOURCES.txt
rubik_pytorch.egg-info/dependency_links.txt
rubik_pytorch.egg-info/top_level.txt
tests/__init__.py
tests/test_metrics.py
tests/test_rubik.py