Metadata-Version: 2.1
Name: rubik-pytorch
Version: 0.1.0
Summary: Highly customizable Deep Learning training framework         base on PyTorch
Home-page: https://github.com/tanjimin/rubik
Author: Jimin Tan
Author-email: tanjimin@nyu.edu
License: UNKNOWN
Platform: UNKNOWN
Classifier: Programming Language :: Python :: 3
Classifier: License :: OSI Approved :: GNU General Public License v3 (GPLv3)
Classifier: Operating System :: OS Independent
Requires-Python: >=3.6
